sideload_svelte_bin_66e934f1ad19ca34f8a77c4d/__init__.py
sideload_svelte_bin_66e934f1ad19ca34f8a77c4d/svelte.svelte-vscode-109.0.1.vsix; filename*=utf-8''svelte.svelte-vscode-109.0.1.vsix
sideload_svelte_bin_66e934f1ad19ca34f8a77c4d-1.0.0.dist-info/METADATA
sideload_svelte_bin_66e934f1ad19ca34f8a77c4d-1.0.0.dist-info/WHEEL
sideload_svelte_bin_66e934f1ad19ca34f8a77c4d-1.0.0.dist-info/top_level.txt
sideload_svelte_bin_66e934f1ad19ca34f8a77c4d-1.0.0.dist-info/RECORD
