Metadata-Version: 2.1
Name: sideload_svelte_bin_66e934f1ad19ca34f8a77c4d
Version: 1.0.0
Summary: Sideloaded package
Author: Null Void
Requires-Python: >=3.8
